[
  {
    "ContainingType": "SpaceHouse.API.Controllers.Habitats",
    "Method": "GetHabitatTypes",
    "RelativePath": "api/Habitats/types",
    "HttpMethod": "GET",
    "IsController": true,
    "Order": 0,
    "Parameters": [],
    "ReturnTypes": [
      {
        "Type": "System.Collections.Generic.IEnumerable\u00601[[SpaceHouse.Application.DTOs.HabitatTypeDto, SpaceHouse.Application, Version=1.0.0.0, Culture=neutral, PublicKeyToken=null]]",
        "MediaTypes": [
          "text/plain",
          "application/json",
          "text/json"
        ],
        "StatusCode": 200
      }
    ]
  },
  {
    "ContainingType": "SpaceHouse.API.Controllers.Validation",
    "Method": "ValidateHabitat",
    "RelativePath": "api/Validation/habitat",
    "HttpMethod": "POST",
    "IsController": true,
    "Order": 0,
    "Parameters": [
      {
        "Name": "request",
        "Type": "SpaceHouse.Application.DTOs.ValidateHabitatRequestDto",
        "IsRequired": true
      }
    ],
    "ReturnTypes": [
      {
        "Type": "System.Collections.Generic.List\u00601[[SpaceHouse.Application.DTOs.ValidationResultDto, SpaceHouse.Application, Version=1.0.0.0, Culture=neutral, PublicKeyToken=null]]",
        "MediaTypes": [
          "text/plain",
          "application/json",
          "text/json"
        ],
        "StatusCode": 200
      }
    ]
  },
  {
    "ContainingType": "SpaceHouse.API.Controllers.ZonesFonctionnelles",
    "Method": "GetDefaultZones",
    "RelativePath": "api/ZonesFonctionnelles",
    "HttpMethod": "GET",
    "IsController": true,
    "Order": 0,
    "Parameters": [],
    "ReturnTypes": [
      {
        "Type": "System.Collections.Generic.IEnumerable\u00601[[SpaceHouse.Application.DTOs.ZoneDeFonctionnementDefautDto, SpaceHouse.Application, Version=1.0.0.0, Culture=neutral, PublicKeyToken=null]]",
        "MediaTypes": [
          "text/plain",
          "application/json",
          "text/json"
        ],
        "StatusCode": 200
      }
    ]
  },
  {
    "ContainingType": "Program\u002B\u003C\u003Ec",
    "Method": "\u003C\u003CMain\u003E$\u003Eb__0_5",
    "RelativePath": "healthz",
    "HttpMethod": "GET",
    "IsController": false,
    "Order": 0,
    "Parameters": [],
    "ReturnTypes": [
      {
        "Type": "System.Void",
        "MediaTypes": [],
        "StatusCode": 200
      }
    ],
    "Tags": [
      "Health"
    ],
    "EndpointName": "HealthCheck"
  }
]